insyde/__init__.py
insyde/main.py
insyde/playground.py
insyde/uber_example.py
insyde-0.0.1.dist-info/METADATA
insyde-0.0.1.dist-info/WHEEL
insyde-0.0.1.dist-info/top_level.txt
insyde-0.0.1.dist-info/RECORD
